aws_recommendation_a1/__init__.py
aws_recommendation_a1/cloudwatch.py
aws_recommendation_a1/cost_estimations.py
aws_recommendation_a1/ebs.py
aws_recommendation_a1/ec2.py
aws_recommendation_a1/elb.py
aws_recommendation_a1/rds.py
aws_recommendation_a1/recommendation.py
aws_recommendation_a1/redshift.py
aws_recommendation_a1/s3.py
aws_recommendation_a1/truted_advisor.py
aws_recommendation_a1/utils.py
aws_recommendation_a1-0.0.13.dist-info/LICENCE
aws_recommendation_a1-0.0.13.dist-info/METADATA
aws_recommendation_a1-0.0.13.dist-info/WHEEL
aws_recommendation_a1-0.0.13.dist-info/top_level.txt
aws_recommendation_a1-0.0.13.dist-info/RECORD
