Metadata-Version: 2.1
Name: aws-recommendation-a1
Version: 0.0.13
Summary: Provides AWS recommendations
Author-email: "dheeraj.banodha" <dheerajmbanodha@gmail.com>
Classifier: Programming Language :: Python :: 3
Classifier: Operating System :: OS Independent
Requires-Python: >=3.7
License-File: LICENCE
